cs/hashindex.py
cs_hashindex-20250531.dist-info/entry_points.txt
cs_hashindex-20250531.dist-info/WHEEL
cs_hashindex-20250531.dist-info/METADATA
cs_hashindex-20250531.dist-info/RECORD
