Metadata-Version: 2.4
Name: cs-hashindex
Version: 20250531
Summary: A command and utility functions for making listings of file content hashcodes and manipulating directory trees based on such a hash index.
Keywords: python3
Author-email: Cameron Simpson <cs@cskk.id.au>
Classifier: Programming Language :: Python
Classifier: Programming Language :: Python :: 3
Classifier: Development Status :: 4 - Beta
Classifier: Intended Audience :: Developers
Classifier: Operating System :: OS Independent
Classifier: Topic :: Software Development :: Libraries :: Python Modules
Classifier: License :: OSI Approved :: GNU General Public License v3 or later (GPLv3+)
Requires-Dist: blake3
Requires-Dist: cs.cmdutils>=20240211
Requires-Dist: cs.context>=20250528
Requires-Dist: cs.deco>=20250531
Requires-Dist: cs.fs>=20250528
Requires-Dist: cs.fstags>=20250528
Requires-Dist: cs.hashutils>=20250414.1
Requires-Dist: cs.lex>=20250428
Requires-Dist: cs.logutils>=20250323
Requires-Dist: cs.pfx>=20250308
Requires-Dist: cs.psutils>=20250513
Requires-Dist: cs.resources>=20250325
Requires-Dist: cs.upd>=20250426
Requires-Dist: icontract
Requires-Dist: typeguard
Project-URL: MonoRepo Commits, https://bitbucket.org/cameron_simpson/css/commits/branch/main
Project-URL: Monorepo Git Mirror, https://github.com/cameron-simpson/css
Project-URL: Monorepo Hg/Mercurial Mirror, https://hg.sr.ht/~cameron-simpson/css
Project-URL: Source, https://github.com/cameron-simpson/css/blob/main/lib/python/cs/hashindex.py
